video_dl/__init__.py
video_dl/args.py
video_dl/danmaku.py
video_dl/entry.py
video_dl/extractor.py
video_dl/spider.py
video_dl/toolbox.py
video_dl/video.py
video_dl/resource/ass_header.txt
video_dl/resource/config.json
video_dl/resource/ixigua_acrawler.js
video_dl/resource/user_agents.txt
video_dl/sites/__init__.py
video_dl/sites/bilibili/__init__.py
video_dl/sites/bilibili/dm_pb2.py
video_dl/sites/bilibili/extractor.py
video_dl/sites/bilibili/json2ass.py
video_dl/sites/bilibili/spider.py
video_dl/sites/ixigua/__init__.py
video_dl/sites/ixigua/extractor.py
video_dl/sites/ixigua/spider.py
video_dl/sites/pornhub/__init__.py
video_dl/sites/pornhub/extractor.py
video_dl/sites/pornhub/spider.py
video_dl/sites/xvideos/__init__.py
video_dl/sites/xvideos/extractor.py
video_dl/sites/xvideos/spider.py
video_dl-0.0.17.dist-info/LICENSE
video_dl-0.0.17.dist-info/METADATA
video_dl-0.0.17.dist-info/WHEEL
video_dl-0.0.17.dist-info/entry_points.txt
video_dl-0.0.17.dist-info/top_level.txt
video_dl-0.0.17.dist-info/RECORD
