Metadata-Version: 2.1
Name: video-dl
Version: 0.0.17
Summary: A naive online video downloader based on aiohttp
Home-page: https://github.com/fengdongfa1995/video-dl
Author: StableGenius
Author-email: fengdongfa1995@163.com
License: APACHE LICENSE, VERSION 2.0
Project-URL: Bug Tracker, https://github.com/fengdongfa1995/video-dl/issues
Keywords: video downloader,aiohttp
Platform: UNKNOWN
Classifier: Development Status :: 3 - Alpha
Classifier: Environment :: Console
Classifier: Framework :: AsyncIO
Classifier: Intended Audience :: End Users/Desktop
Classifier: License :: OSI Approved :: Apache Software License
Classifier: Natural Language :: Chinese (Simplified)
Classifier: Natural Language :: English
Classifier: Operating System :: OS Independent
Classifier: Programming Language :: Python :: 3 :: Only
Classifier: Programming Language :: Python :: 3.8
Classifier: Programming Language :: Python :: 3.9
Classifier: Programming Language :: Python :: 3.10
Classifier: Topic :: Internet
Classifier: Topic :: Utilities
Requires-Python: >=3.8
License-File: LICENSE
Requires-Dist: aiohttp
Requires-Dist: prettytable
Requires-Dist: protobuf
Requires-Dist: uvloop ; platform_system == "Linux"
